sloancone/.DS_Store
sloancone/__init__.py
sloancone/__version__.py
sloancone/check_coverage.py
sloancone/cl_utils.py
sloancone/cone_search.py
sloancone/default_settings.yaml
sloancone/image.py
sloancone/sdss_square_search.py
sloancone/test_settings.yaml
sloancone/utKit.py
sloancone/commonutils/__init__.py
sloancone/commonutils/getpackagepath.py
sloancone/resources/package.mplstyle
sloancone/tests/__init__.py
sloancone/tests/test_check_coverage.py
sloancone/tests/test_cl_utils.py
sloancone/tests/test_cone_search.py
sloancone/tests/test_image.py
sloancone/tests/test_sdss_square_search.py
sloancone-0.4.3.dist-info/LICENSE
sloancone-0.4.3.dist-info/METADATA
sloancone-0.4.3.dist-info/WHEEL
sloancone-0.4.3.dist-info/entry_points.txt
sloancone-0.4.3.dist-info/top_level.txt
sloancone-0.4.3.dist-info/RECORD
