Metadata-Version: 2.1
Name: sloancone
Version: 0.4.3
Summary: SDSS conesearching tools via the CL or Python API. Return conesearch results, or simply check whether or not a location in the sky has been covered by SDSS.
Home-page: https://github.com/thespacedoctor/sloancone
Download-URL: https://github.com/thespacedoctor/sloancone/archive/v0.4.3.zip
Author: David Young
Author-email: davidrobertyoung@gmail.com
License: MIT
Keywords: astronomy, conesearch, sdss
Classifier: Development Status :: 4 - Beta
Classifier: License :: OSI Approved :: MIT License
Classifier: Programming Language :: Python :: 3.9
Classifier: Topic :: Utilities
License-File: LICENSE
Requires-Dist: pyyaml
Requires-Dist: sloancone
Requires-Dist: fundamentals
Requires-Dist: python-dateutil
Requires-Dist: astrocalc
Requires-Dist: requests
Requires-Dist: eventlet
Requires-Dist: unicodecsv
Requires-Dist: numpy
